pinpoint/__init__.py
pinpoint/config.py
pinpoint/core.py
pinpoint/prepare.py
pinpoint/data/post_code_cn.json
pinpoint/data/post_code_kr.txt
pinpoint/data/post_code_tw.txt
PinPoint-0.2.1.dist-info/LICENSE.txt
PinPoint-0.2.1.dist-info/METADATA
PinPoint-0.2.1.dist-info/WHEEL
PinPoint-0.2.1.dist-info/top_level.txt
PinPoint-0.2.1.dist-info/zip-safe
PinPoint-0.2.1.dist-info/RECORD
