Metadata-Version: 2.1
Name: PinPoint
Version: 0.2.1
Summary: A fast geo toolkit for academic affiliation strings
Home-page: http://pinpoint.eckert.science
Author: Hagen Eckert
Author-email: pinpoint@eckert.science
License: MIT
Download-URL: https://bitbucket.org/nathan-diodan/pinpoint/get/0.2.1.zip
Keywords: collaboration metrics,weighted distance,cooperation distance,apparent location,affiliation strings,bibliometrics
Platform: UNKNOWN
Classifier: Development Status :: 4 - Beta
Classifier: Intended Audience :: Science/Research
Classifier: Topic :: Scientific/Engineering :: Information Analysis
Classifier: License :: OSI Approved :: MIT License
Classifier: Operating System :: OS Independent
Classifier: Programming Language :: Python :: 3.6
Classifier: Programming Language :: Python :: 3.7
Classifier: Programming Language :: Python :: 3 :: Only
Requires-Python: ~=3.6
Requires-Dist: appdirs
Requires-Dist: geopy
Requires-Dist: numpy
Requires-Dist: nvector
Requires-Dist: scipy
Requires-Dist: unidecode
